choc_expr/__init__.py
choc_expr/attr.py
choc_expr/expr.py
choc_expr/utils.py
choc_expr-1.3.5.dist-info/LICENSE
choc_expr-1.3.5.dist-info/METADATA
choc_expr-1.3.5.dist-info/WHEEL
choc_expr-1.3.5.dist-info/top_level.txt
choc_expr-1.3.5.dist-info/RECORD
