Metadata-Version: 2.1
Name: choc-expr
Version: 1.3.5
Summary: A Python templating library
Home-page: https://github.com/pe-brian/choc-expr
Author: Pierre-Emmanuel Brian
Author-email: pebrian@outlook.fr
Project-URL: Bug Tracker, https://github.com/pe-brian/choc-expr/issues
Classifier: Programming Language :: Python :: 3
Classifier: License :: OSI Approved :: MIT License
Classifier: Operating System :: OS Independent
Requires-Python: >=3.12.2
License-File: LICENSE
Requires-Dist: typeguard ==4.3.0
